{
  "name": "LJTestPods",
  "version": "0.1.3",
  "summary": "A short description of LJTestPods.",
  "description": "TODO: Add long description of the pod here.",
  "homepage": "https://bitbucket.devops.nonprod.empf.local/scm/react/LJTestPods",
  "license": {
    "type": "MIT",
    "file": "LICENSE"
  },
  "authors": {
    "dabaosodmi0420": "zhenglianjie@csc.com.cn"
  },
  "source": {
    "git": "https://bitbucket.devops.nonprod.empf.local/scm/react/LJTestPods.git",
    "tag": "0.1.3"
  },
  "platforms": {
    "ios": "8.0"
  },
  "source_files": "LJTestPods/Classes/**/*",
  "resource_bundles": {
    "LJTestPods": [
      "LJTestPods/Assets/LJTestPods/*.png"
    ]
  },
  "frameworks": "UIKit"
}
