{
  "name": "Butterfly",
  "version": "0.1.1",
  "license": "MIT",
  "summary": "Integrate feedback module elegantly.",
  "authors": {
    "Wongzigii": "https://github.com/wongzigii"
  },
  "homepage": "https://bitbucket.devops.nonprod.empf.local/scm/react/Butterfly",
  "source": {
    "git": "https://bitbucket.devops.nonprod.empf.local/scm/react/Butterfly.git",
    "tag": "0.1.1"
  },
  "platforms": {
    "ios": "8.0"
  },
  "source_files": "Butterfly/*.{h,swift}",
  "ios": {
    "resource_bundles": {
      "Butterfly": "Butterfly/Logo/*.png"
    }
  }
}
