{
  "name": "SWebViewImageDownload",
  "version": "0.0.2",
  "summary": "取得網頁或HTML Body內的imageURL",
  "homepage": "https://bitbucket.devops.nonprod.empf.local/scm/react/SWebViewImageDownload",
  "license": "MIT",
  "authors": {
    "alexchueh": "shadow@pixnet.tw"
  },
  "platforms": {
    "ios": "8.0"
  },
  "source": {
    "git": "https://bitbucket.devops.nonprod.empf.local/scm/react/SWebViewImageDownload",
    "tag": "1.0.1"
  },
  "source_files": [
    "SWebViewImageDownload",
    "*.{h,m}"
  ],
  "exclude_files": "Classes/Exclude",
  "requires_arc": true
}
