{
  "name": "webrtc-bitcode",
  "version": "63.1",
  "summary": "Prebuilt WebRTC Framework with bitcode enabled",
  "description": "Prebuilt WebRTC iOS Dynamic Framework with bitcode enabled",
  "homepage": "https://bitbucket.devops.nonprod.empf.local/scm/react/webrtc-bitcode",
  "license": {
    "type": "MIT",
    "file": "LICENSE"
  },
  "authors": {
    "Andrew Ryan": "aryan@cafex.com"
  },
  "source": {
    "git": "https://bitbucket.devops.nonprod.empf.local/scm/react/webrtc-bitcode.git",
    "tag": "63.1"
  },
  "vendored_frameworks": "WebRTC.framework",
  "platforms": {
    "ios": "9.0"
  },
  "requires_arc": true
}
