{
  "name": "PGImagePicker",
  "version": "1.1.0",
  "summary": "多图浏览",
  "homepage": "https://bitbucket.devops.nonprod.empf.local/scm/react/PGImagePicker",
  "license": "MIT",
  "authors": {
    "piggybear": "piggybear_net@163.com"
  },
  "platforms": {
    "ios": "8.0"
  },
  "source": {
    "git": "https://bitbucket.devops.nonprod.empf.local/scm/react/PGImagePicker.git",
    "tag": "1.1.0"
  },
  "source_files": [
    "PGImagePicker",
    "PGImagePicker/**/*.swift"
  ],
  "frameworks": "UIKit",
  "requires_arc": true,
  "dependencies": {
    "PGActionSheet": [

    ]
  },
  "pushed_with_swift_version": "3.0"
}
