{
  "name": "SmartUI",
  "version": "0.9.11",
  "summary": "SwiftUI inspired framework which uses the same syntax and provides support for iOS 10 and above",
  "homepage": "https://bitbucket.devops.nonprod.empf.local/scm/react/SmartUI",
  "license": {
    "type": "MIT",
    "file": "LICENSE"
  },
  "authors": {
    "Igor Tiukavkin": "in.tyukavkin@gmail.com"
  },
  "source": {
    "git": "https://bitbucket.devops.nonprod.empf.local/scm/react/SmartUI.git",
    "tag": "0.9.11"
  },
  "platforms": {
    "ios": "10.0"
  },
  "swift_versions": "5.0",
  "source_files": "SmartUI/Sources/**/*",
  "swift_version": "5.0"
}
