{
  "name": "FndBanner",
  "version": "0.1.0",
  "summary": "A short description of FndBanner.",
  "description": "TODO: Add long description of the pod here.",
  "homepage": "https://bitbucket.devops.nonprod.empf.local/scm/react/FndBanner",
  "license": {
    "type": "MIT",
    "file": "LICENSE"
  },
  "authors": {
    "lushaoxiong": "18634324168@163.com"
  },
  "source": {
    "git": "https://bitbucket.devops.nonprod.empf.local/scm/react/FndBanner.git",
    "tag": "0.1.0"
  },
  "platforms": {
    "ios": "8.0"
  },
  "source_files": "FndBanner/Classes/**/*",
  "dependencies": {
    "SDWebImage": [

    ]
  }
}
