{
  "name": "AppBack",
  "version": "0.1.1",
  "summary": "A short description of AppBack.",
  "description": "TODO: Add long description of the pod here.",
  "homepage": "https://bitbucket.devops.nonprod.empf.local/scm/react/appback-ios",
  "license": {
    "type": "MIT",
    "file": "LICENSE"
  },
  "authors": {
    "appback": "support@appback.io"
  },
  "source": {
    "git": "https://bitbucket.devops.nonprod.empf.local/scm/react/appback-ios",
    "tag": "0.1.1"
  },
  "platforms": {
    "ios": "8.0"
  },
  "source_files": "Classes/**/*"
}
