{
  "name": "CHAnimationLabel",
  "version": "1.2.4",
  "summary": "label动画",
  "description": "TODO: Add long description of the pod here.",
  "homepage": "https://bitbucket.devops.nonprod.empf.local/scm/react/CHAnimationLabel",
  "license": {
    "type": "MIT",
    "file": "LICENSE"
  },
  "authors": {
    "杨胜浩": "chuqingr@icloud.com"
  },
  "source": {
    "git": "https://bitbucket.devops.nonprod.empf.local/scm/react/CHAnimationLabel.git",
    "tag": "1.2.4"
  },
  "platforms": {
    "ios": "8.0"
  },
  "requires_arc": true,
  "source_files": "CHAnimationLabel/Classes/**/*"
}
