{
  "name": "ScreenCorners",
  "version": "1.0.0",
  "license": {
    "type": "MIT"
  },
  "homepage": "https://bitbucket.devops.nonprod.empf.local/scm/react/ScreenCorners",
  "authors": {
    "Kyle Bashour": "kylebshr@me.com"
  },
  "summary": "Screen corner radius for iOS devices.",
  "source": {
    "git": "https://bitbucket.devops.nonprod.empf.local/scm/react/ScreenCorners.git",
    "tag": "v1.0.0"
  },
  "swift_versions": "5.1",
  "platforms": {
    "ios": "12.1"
  },
  "source_files": "Sources/ScreenCorners/*.swift",
  "ios": {
    "frameworks": "UIKit"
  },
  "swift_version": "5.1"
}
