{
  "name": "JDFlutter",
  "version": "0.4.0",
  "summary": "A short description of JDFlutter.",
  "description": "TA short description of JDFlutter.",
  "homepage": "https://bitbucket.devops.nonprod.empf.local/scm/react/JDFlutter",
  "license": {
    "type": "MIT"
  },
  "authors": {
    "jiedi": "571502887@qq.com"
  },
  "source": {
    "git": "https://bitbucket.devops.nonprod.empf.local/scm/react/JDFlutter.git",
    "tag": "0.4.0"
  },
  "platforms": {
    "ios": "9.0"
  },
  "source_files": "JDFlutter/Classes/**/*"
}
