{
  "name": "SimpleREST",
  "version": "0.1.5",
  "summary": "Simple REST client",
  "description": "Simple REST client with ability to cache response data",
  "homepage": "https://bitbucket.devops.nonprod.empf.local/scm/react/SimpleREST",
  "license": {
    "type": "MIT",
    "file": "LICENSE"
  },
  "authors": {
    "alexander-gaidukov": "alexander.gaidukov@gmail.com"
  },
  "source": {
    "git": "https://bitbucket.devops.nonprod.empf.local/scm/react/SimpleREST.git",
    "tag": "0.1.5"
  },
  "platforms": {
    "ios": "9.0"
  },
  "source_files": "SimpleREST/Classes/**/*",
  "pushed_with_swift_version": "4.0"
}
