{
  "name": "AEImage",
  "version": "2.1.0",
  "license": {
    "type": "MIT",
    "file": "LICENSE"
  },
  "summary": "Adaptive image viewer for iOS (with support for zoom, gyro motion and infinite scroll)",
  "homepage": "https://bitbucket.devops.nonprod.empf.local/scm/react/AEImage",
  "authors": {
    "tadija": "tadija@me.com"
  },
  "social_media_url": "http://twitter.com/tadija",
  "source": {
    "git": "https://bitbucket.devops.nonprod.empf.local/scm/react/AEImage.git",
    "tag": "2.1.0"
  },
  "source_files": "Sources/*.swift",
  "pod_target_xcconfig": {
    "SWIFT_VERSION": "3.0"
  },
  "platforms": {
    "ios": "9.0"
  },
  "pushed_with_swift_version": "3.0"
}
