{
  "name": "Gloss",
  "version": "0.5.2",
  "summary": "A shiny JSON parsing library in Swift",
  "homepage": "https://bitbucket.devops.nonprod.empf.local/scm/react/Gloss",
  "license": {
    "type": "MIT",
    "file": "LICENSE"
  },
  "authors": {
    "Harlan Kellaway": "hello@harlankellaway.com"
  },
  "source": {
    "git": "https://bitbucket.devops.nonprod.empf.local/scm/react/Gloss.git",
    "tag": "0.5.2"
  },
  "platforms": {
    "ios": "8.0"
  },
  "requires_arc": true,
  "source_files": "Source/*.{swift}"
}
