{
  "name": "pushwoosh-ios-arc-sdk",
  "version": "0.1",
  "summary": "Pushwoosh iOS SDK with ARC support",
  "description": "\t\t\t\t  Pushwoosh iOS SDK with ARC support. For seamless integration of PushWoosh with your iOS app. \n",
  "homepage": "https://bitbucket.devops.nonprod.empf.local/scm/react/pushwoosh-ios-arc-sdk",
  "license": "MIT",
  "authors": {
    "Pawel 'Kender' Maczewski": "kender@codingslut.com"
  },
  "source": {
    "git": "https://bitbucket.devops.nonprod.empf.local/scm/react/pushwoosh-ios-arc-sdk.git",
    "tag": "0.1"
  },
  "platforms": {
    "ios": "5.0"
  },
  "requires_arc": true,
  "source_files": "Classes/*",
  "resources": [
    "LICENSE",
    "README.md"
  ]
}
