{
  "name": "FakeTencent",
  "version": "3.3.3",
  "summary": "FakeTencent",
  "description": "FakeTencent for CocoaPods",
  "homepage": "https://bitbucket.devops.nonprod.empf.local/scm/react/FakeTencent",
  "license": {
    "type": "MIT",
    "file": "LICENSE"
  },
  "authors": {
    "v7lin": "v7lin@qq.com"
  },
  "source": {
    "git": "https://bitbucket.devops.nonprod.empf.local/scm/react/FakeTencent.git",
    "tag": "3.3.3"
  },
  "platforms": {
    "ios": "8.0"
  },
  "vendored_frameworks": "FakeTencent/Tencent/*.framework",
  "frameworks": "SystemConfiguration",
  "libraries": "stdc++"
}
