{
  "name": "AAKeyboardManager",
  "version": "0.1.0",
  "summary": "Keyboard manager for quickly integrating animations",
  "homepage": "https://bitbucket.devops.nonprod.empf.local/scm/react/AAKeyboardManager",
  "license": "MIT",
  "authors": {
    "Anıl Anar": "anilanar@hotmail.com"
  },
  "source": {
    "git": "https://bitbucket.devops.nonprod.empf.local/scm/react/AAKeyboardManager.git",
    "tag": "0.1.0"
  },
  "platforms": {
    "ios": "7.1"
  },
  "requires_arc": true,
  "source_files": "Pod/Classes/**/*",
  "frameworks": [
    "UIKit",
    "Foundation"
  ]
}
