{
  "name": "UIGestureRecognizer+ReactiveCocoa",
  "version": "0.1.0",
  "summary": "Handle gestures with ReactiveCocoa! No more ugly selectors!",
  "homepage": "https://bitbucket.devops.nonprod.empf.local/scm/react/UIGestureRecognizer-RACExtension",
  "license": "MIT",
  "authors": {
    "kaiinui": "lied.der.optik@gmail.com"
  },
  "source": {
    "git": "https://bitbucket.devops.nonprod.empf.local/scm/react/UIGestureRecognizer-RACExtension.git",
    "tag": "v0.1.0"
  },
  "source_files": "GestureRecognizerRACExt/Classes/**/*.{h,m}",
  "requires_arc": true,
  "platforms": {
    "ios": "7.0"
  },
  "dependencies": {
    "ReactiveCocoa": [

    ]
  }
}
