{
  "name": "HLPopMenu",
  "version": "1.0.1",
  "summary": "A short description of HLCirclyMenu.",
  "description": "TODO: Add long description of the pod here.",
  "homepage": "https://bitbucket.devops.nonprod.empf.local/scm/react/HLPopMenu",
  "license": {
    "type": "MIT",
    "file": "LICENSE"
  },
  "authors": {
    "levihan": "weakstrongself@gmail.com"
  },
  "source": {
    "git": "https://bitbucket.devops.nonprod.empf.local/scm/react/HLPopMenu.git",
    "tag": "1.0.1"
  },
  "platforms": {
    "ios": "7.0"
  },
  "source_files": "HLPopMenu/Classes/**/*"
}
