{
  "name": "FKTableView",
  "version": "1.2.0",
  "summary": "UITableView的友好扩展",
  "homepage": "https://bitbucket.devops.nonprod.empf.local/scm/react/FKTableView",
  "license": {
    "type": "MIT",
    "file": "LICENSE"
  },
  "authors": {
    "CHAT": "312163862@qq.com"
  },
  "source": {
    "git": "https://bitbucket.devops.nonprod.empf.local/scm/react/FKTableView.git",
    "tag": "1.2.0"
  },
  "platforms": {
    "ios": "8.0"
  },
  "requires_arc": true,
  "dependencies": {
    "FKTableCollectionExtensionBase": [

    ]
  },
  "source_files": "FKTableView/FKTableView/Classes/*.{h,m}"
}
