{
  "name": "PopoverObjC",
  "version": "0.1.0",
  "summary": "ObjC version of popover(https://bitbucket.devops.nonprod.empf.local/scm/react/Popover).",
  "description": "TODO: Add long description of the pod here.",
  "homepage": "https://bitbucket.devops.nonprod.empf.local/scm/react/PopoverObjC",
  "license": {
    "type": "MIT",
    "file": "LICENSE"
  },
  "authors": {
    "Assuner": "assuner@foxmail.com"
  },
  "source": {
    "git": "https://bitbucket.devops.nonprod.empf.local/scm/react/PopoverObjC.git",
    "tag": "0.1.0"
  },
  "platforms": {
    "ios": "8.0"
  },
  "source_files": "PopoverObjC/Classes/**/*"
}
