{
  "name": "DCQRCode",
  "version": "1.0",
  "summary": "Scan and generate QRCode or BarCode using AVFoundation",
  "homepage": "https://bitbucket.devops.nonprod.empf.local/scm/react/DCQRCode",
  "license": {
    "type": "MIT",
    "text": "The DCTaskReactor use the MIT license"
  },
  "authors": {
    "Tangdixi": "Tangdixi@gmail.com"
  },
  "platforms": {
    "ios": "7.0"
  },
  "source": {
    "git": "https://bitbucket.devops.nonprod.empf.local/scm/react/DCQRCode.git",
    "tag": "1.0"
  },
  "source_files": "DCQRCode/*.{h,m}",
  "frameworks": [
    "Foundation",
    "UIKit",
    "CoreImage",
    "AVFoundation"
  ],
  "requires_arc": true
}
