{
  "name": "CCCategory",
  "version": "0.0.2",
  "summary": "一些常用的Category,目前包括(Foundation,MapKit,QuartzCore,UIKit),后续不断更新.",
  "homepage": "https://bitbucket.devops.nonprod.empf.local/scm/react/CCCategory",
  "license": "MIT",
  "authors": {
    "MuZiLee": "lifeiheng132@gmail.com"
  },
  "platforms": {
    "ios": "7.0"
  },
  "source": {
    "git": "https://bitbucket.devops.nonprod.empf.local/scm/react/CCCategory.git",
    "tag": "0.0.2"
  },
  "source_files": "CCCategory+Tags/*.{h,m}",
  "frameworks": [
    "Foundation",
    "MapKit",
    "QuartzCore",
    "UIKit"
  ]
}
