{
  "name": "WeexGcanvas",
  "version": "0.1.2",
  "summary": "GCanvas Weex Bridge Source.",
  "description": "GCanvas Weex Bridge Source.",
  "homepage": "https://bitbucket.devops.nonprod.empf.local/scm/react/GCanvas",
  "license": {
    "type": "Copyright",
    "text": "           Alibaba-INC copyright\n"
  },
  "authors": {
    "jwxbond": "jwxbond@gmail.com"
  },
  "platforms": {
    "ios": "8.0"
  },
  "source": {
    "git": "https://bitbucket.devops.nonprod.empf.local/scm/react/GCanvas.git",
    "tag": "0.1.2"
  },
  "source_files": "GCanvas/bridges/weex-bridge/ios/sdk/Sources/*.{h,m}",
  "public_header_files": "GCanvas/bridges/weex-bridge/ios/sdk/Sources/*.h",
  "user_target_xcconfig": {
    "FRAMEWORK_SEARCH_PATHS": "'$(PODS_ROOT)/WeexGcanvas'"
  },
  "requires_arc": true,
  "dependencies": {
    "WeexPluginLoader": [

    ],
    "WeexSDK": [

    ],
    "GCanvas": [

    ],
    "SDWebImage": [

    ]
  },
  "libraries": "stdc++"
}
