{
  "name": "SemanticVersioning",
  "version": "1.0.0-beta",
  "license": {
    "type": "MIT"
  },
  "summary": "Elegant Semantic Versioning in Swift",
  "homepage": "https://bitbucket.devops.nonprod.empf.local/scm/react/SemanticVersioning",
  "social_media_url": "http://twitter.com/Ajax64",
  "authors": {
    "Alexander Ney": "alexander.ney@me.com"
  },
  "source": {
    "git": "https://bitbucket.devops.nonprod.empf.local/scm/react/SemanticVersioning.git",
    "branch": "master",
    "tag": "v1.0.0-beta"
  },
  "requires_arc": true,
  "platforms": {
    "ios": "8.0",
    "osx": "10.9"
  },
  "source_files": "Source/*.swift"
}
