{
  "name": "CommonFramework",
  "version": "0.1.0",
  "summary": "CommonFramework",
  "description": "This is framework was made by me",
  "homepage": "https://bitbucket.devops.nonprod.empf.local/scm/react/CommonFramework",
  "license": "MIT",
  "authors": {
    "Duy Nguyen": "tam.nguyen@watasolutions.com"
  },
  "platforms": {
    "ios": "13.0"
  },
  "source": {
    "git": "https://bitbucket.devops.nonprod.empf.local/scm/react/CommonFramework.git",
    "tag": "0.1.0"
  },
  "source_files": "CommonFramework/**/*.{h,m}",
  "requires_arc": true
}
