{
  "name": "MJMeteorView",
  "version": "1.0.0",
  "summary": "Effect of particle: meteor view.",
  "homepage": "https://bitbucket.devops.nonprod.empf.local/scm/react/MJMeteorView",
  "license": {
    "type": "MIT",
    "file": "LICENSE"
  },
  "authors": {
    "iosLiuPeng": "392009255@qq.com"
  },
  "source": {
    "git": "https://bitbucket.devops.nonprod.empf.local/scm/react/MJMeteorView.git",
    "tag": "1.0.0"
  },
  "platforms": {
    "ios": "7.0"
  },
  "source_files": "Classes/*.{h,m}",
  "frameworks": "UIKit",
  "resource_bundles": {
    "img_meteor": [
      "Assets/*.png"
    ]
  }
}
