{
  "name": "TradPlusKidozSDK",
  "version": "8.9.3",
  "summary": "TradPlusKidozSDK",
  "description": "TradPlusKidozSDK,TradPlusKidozSDK,Kidoz",
  "homepage": "https://bitbucket.devops.nonprod.empf.local/scm/react/TradPlusKidozSDK",
  "license": {
    "type": "MIT",
    "file": "LICENSE"
  },
  "authors": {
    "TradPlus": "ios"
  },
  "source": {
    "git": "https://bitbucket.devops.nonprod.empf.local/scm/react/TradPlusKidozSDK.git",
    "tag": "8.9.3"
  },
  "platforms": {
    "ios": "9.0"
  },
  "requires_arc": true,
  "frameworks": [
    "SystemConfiguration",
    "CoreGraphics",
    "Foundation",
    "UIKit"
  ],
  "pod_target_xcconfig": {
    "OTHER_LDFLAGS": [
      "-lObjC"
    ]
  },
  "libraries": [
    "c++",
    "z",
    "sqlite3",
    "xml2",
    "resolv"
  ],
  "source_files": "KidozSDK/*.h",
  "vendored_libraries": "KidozSDK/libKidozSDK.a"
}
