{
  "name": "Whiteboard",
  "version": "0.0.2",
  "summary": "netless.io Whiteboard API on iOS",
  "description": "White-SDK-iOS 的开源版本实现，基于 White-SDK-iOS 2.4.18 继续开发",
  "homepage": "https://bitbucket.devops.nonprod.empf.local/scm/react/whiteboard-ios",
  "license": {
    "type": "MIT",
    "file": "LICENSE"
  },
  "authors": {
    "leavesster": "yleaf@herewhite.com"
  },
  "source": {
    "git": "https://bitbucket.devops.nonprod.empf.local/scm/react/Whiteboard-iOS.git",
    "tag": "0.0.2"
  },
  "platforms": {
    "ios": "9.0"
  },
  "resource_bundles": {
    "WhiteSDK": [
      "WhiteSDK/Resource/*"
    ]
  },
  "source_files": [
    "WhiteSDK/Classes/**",
    "WhiteSDK/Classes/**/**"
  ],
  "dependencies": {
    "dsBridge": [
      "~> 3.0.2"
    ],
    "YYModel": [
      "~> 1.0.4"
    ]
  },
  "frameworks": [
    "UIKit",
    "WebKit",
    "AVFoundation"
  ]
}
