{
  "name": "MHlibs",
  "version": "0.0.4",
  "summary": "commons libs for normal iOS project",
  "description": "commons libs for normal iOS project",
  "homepage": "https://bitbucket.devops.nonprod.empf.local/scm/react/MHlibs",
  "license": "MIT",
  "authors": {
    "Macro": "macroios@126.com"
  },
  "platforms": {
    "ios": null
  },
  "source": {
    "git": "https://bitbucket.devops.nonprod.empf.local/scm/react/MHlibs.git",
    "tag": "0.0.4"
  },
  "source_files": "MHlibs/DEFINE.h",
  "requires_arc": true
}
