{
  "name": "LEFlatButton",
  "version": "0.1.2",
  "summary": "Simple Flat UIButton",
  "description": "LEFlatButton is a UIButton subclass with a flat style",
  "homepage": "https://bitbucket.devops.nonprod.empf.local/scm/react/LEFlatButton",
  "screenshots": "https://bitbucket.devops.nonprod.empf.local/scm/react/LEFlatButton/raw/master/Screenshots/screenshot.png",
  "license": "MIT",
  "authors": {
    "Lasha Efremidze": "efremidzel@hotmail.com"
  },
  "source": {
    "git": "https://bitbucket.devops.nonprod.empf.local/scm/react/LEFlatButton.git",
    "tag": "0.1.2"
  },
  "social_media_url": "http://linkedin.com/in/efremidze",
  "platforms": {
    "ios": "7.0"
  },
  "requires_arc": true,
  "source_files": "LEFlatButton/*"
}
