{
  "name": "LogStr",
  "version": "0.0.2",
  "summary": "Generate log file locally",
  "description": "Generate log file locally !!Generate log file locally!! Generate log file locally !!Generate log file locally!!",
  "homepage": "https://bitbucket.devops.nonprod.empf.local/scm/react/LogStr",
  "license": "MIT",
  "authors": {
    "zhoucan": "Jax.Zhou@luxshare-ict.com"
  },
  "platforms": {
    "osx": "10.10"
  },
  "source": {
    "git": "https://bitbucket.devops.nonprod.empf.local/scm/react/LogStr.git",
    "tag": "0.0.2"
  },
  "source_files": "TestLog/TestLog/LogStr/*"
}
