{
  "name": "ECPayPaymentKit",
  "version": "0.0.1",
  "summary": "ECPayPaymentKit",
  "homepage": "https://bitbucket.devops.nonprod.empf.local/scm/react/ECPayPaymentKit_iOS",
  "license": {
    "type": "Apache-2.0",
    "file": "LICENSE"
  },
  "authors": {
    "ECPay": "applestore@ecpay.com.tw"
  },
  "platforms": {
    "ios": "10.0"
  },
  "source": {
    "http": "https://bitbucket.devops.nonprod.empf.local/scm/react/ECPayPaymentKit.zip"
  },
  "ios": {
    "vendored_frameworks": "ECPayPaymentKit.framework"
  }
}
