{
  "name": "ScrollPager",
  "version": "0.5",
  "summary": "A fully featured scroll pager similar to the one in flipboard, fully configurable through storyboard",
  "homepage": "https://bitbucket.devops.nonprod.empf.local/scm/react/ScrollPager",
  "license": {
    "type": "MIT",
    "file": "License.txt"
  },
  "authors": {
    "Aryan Ghassemi": "https://bitbucket.devops.nonprod.empf.local/scm/react/ScrollPager"
  },
  "source": {
    "git": "https://bitbucket.devops.nonprod.empf.local/scm/react/ScrollPager.git",
    "tag": "0.5"
  },
  "platforms": {
    "ios": "8.0"
  },
  "source_files": "ScrollPager/Source/*.{swift}",
  "frameworks": [
    "Foundation",
    "UIKit"
  ],
  "requires_arc": true
}
