{
  "name": "EasyConstraint",
  "version": "1.1.0",
  "summary": "Provide some useful APIs for creating iOS layout constraints.",
  "description": "TODO: Add long description of the pod here.",
  "homepage": "https://bitbucket.devops.nonprod.empf.local/scm/react/EasyConstraint",
  "license": {
    "type": "MIT",
    "file": "LICENSE"
  },
  "authors": {
    "lee1994522": "839273739@qq.com"
  },
  "source": {
    "git": "https://bitbucket.devops.nonprod.empf.local/scm/react/EasyConstraint.git",
    "tag": "1.1.0"
  },
  "platforms": {
    "ios": "9.0"
  },
  "source_files": "EasyConstraint/Classes/**/*",
  "public_header_files": "EasyConstraint/Classes/*.h",
  "frameworks": "UIKit"
}
