{
  "name": "DMColorManager",
  "version": "0.1.0",
  "summary": "DMColorManager provide good colors for developing your apps.",
  "description": "DMColorManager provide good colors for developing your apps. You can use great colors which is used in famous apps such as Twitter, Facebook, Instagram and so on.",
  "homepage": "https://bitbucket.devops.nonprod.empf.local/scm/react/DMColorManager",
  "license": {
    "type": "MIT",
    "file": "LICENSE"
  },
  "authors": {
    "masuhara": "info@masuhara.net"
  },
  "source": {
    "git": "https://bitbucket.devops.nonprod.empf.local/scm/react/DMColorManager.git",
    "tag": "0.1.0"
  },
  "social_media_url": "https://twitter.com/masuhara_",
  "platforms": {
    "ios": "8.0"
  },
  "source_files": "DMColorManager/Classes/**/*"
}
