{
  "name": "GLExtensions",
  "version": "0.1.0",
  "summary": "short description.",
  "description": "long description of the pod here.",
  "homepage": "https://bitbucket.devops.nonprod.empf.local/scm/react/GLExtensions",
  "license": {
    "type": "MIT",
    "file": "LICENSE"
  },
  "authors": {
    "liguoliang": "36617161@qq.com"
  },
  "source": {
    "git": "https://bitbucket.devops.nonprod.empf.local/scm/react/GLExtensions.git",
    "tag": "0.1.0"
  },
  "platforms": {
    "ios": "8.0"
  },
  "source_files": "GLExtensions/Classes/**/*"
}
